{"child_modules": [], "data_mtime": 1554169983, "dep_lines": [1, 2, 1, 1], "dep_prios": [10, 5, 5, 30], "dependencies": ["sys", "typing", "builtins", "abc"], "hash": "8ec0450c6aa8b9e61865d2ae39b6328a", "id": "_ast", "ignore_all": true, "interface_hash": "cd779fff2dbd1fa8c854741e29c3ebbe", "mtime": 1554169948, "options": {"allow_redefinition": false, "allow_untyped_globals": false, "always_false": [], "always_true": [], "bazel": false, "check_untyped_defs": false, "disallow_any_decorated": false, "disallow_any_explicit": false, "disallow_any_expr": false, "disallow_any_generics": false, "disallow_any_unimported": false, "disallow_incomplete_defs": false, "disallow_subclassing_any": false, "disallow_untyped_calls": false, "disallow_untyped_decorators": false, "disallow_untyped_defs": false, "follow_imports": "normal", "follow_imports_for_stubs": false, "ignore_errors": false, "ignore_missing_imports": false, "local_partial_types": false, "mypyc": false, "new_semantic_analyzer": false, "no_implicit_optional": false, "platform": "linux", "plugins": [], "show_none_errors": true, "strict_optional": true, "strict_optional_whitelist": null, "warn_no_return": true, "warn_return_any": false, "warn_unused_ignores": false}, "path": "/home/z4r4tu5tr4/.local/share/virtualenvs/Live83-8umqup-x/lib/python3.7/site-packages/mypy/typeshed/stdlib/3/_ast.pyi", "size": 8992, "suppressed": [], "version_id": "0.670"}